django_telegram_logging/__init__.py
django_telegram_logging/apps.py
django_telegram_logging/handler.py
django_telegram_logging-1.0.2.dist-info/METADATA
django_telegram_logging-1.0.2.dist-info/WHEEL
django_telegram_logging-1.0.2.dist-info/top_level.txt
django_telegram_logging-1.0.2.dist-info/RECORD
