Metadata-Version: 2.1
Name: django-telegram-logging
Version: 1.0.2
Summary: An app to send reports over Telegram API
Home-page: https://github.com/Jesrat/django-telegram-logging
Author: Josue Gomez
Author-email: jgomez@jesrat.com
Classifier: Programming Language :: Python :: 3
Classifier: License :: OSI Approved :: Apache Software License
Classifier: Framework :: Django
Classifier: Operating System :: OS Independent
Requires-Dist: django
Requires-Dist: requests
